{"yflhvMFJ//Gncc19l8RWng==":"mbr-1.jpg","T4zkQrDWb0m9qIv27c5rVg==":"mbr-2.jpg","Z0s7uTFMjKcQ7ngLc5lmnA==":"mbr.jpg","wzidloMrha3tuSON+OV1Cw==":"mbr-3.jpg","FhC12xVKkvIETQMVKu9WsA==":"mbr-4.jpg","XLOa+k8BKjlTYw4d/uEulQ==":"mbr-6.jpg","LAL131GPhuSNnoifNS/NrQ==":"mbr.jpeg","n3xLfiICRwBK7qZAxZQ4ig==":"mbr-6.jpeg","61tx7eiw/R1KSuuIhkCgyw==":"mbr-4.jpeg","7BusHJYMZF5vA0Q1cmlFTQ==":"mbr-9.jpeg","YRJAA6ew0xAs6F0Ax5Rfvw==":"mbr-11.jpeg","DUgaHyV9oTcz7ZCUxJbpSQ==":"mbr-2.jpeg","nmaFfquSo95VQKE0s/iKhQ==":"mbr-3.jpeg","fdrkojhpw03cB3GSjvgDuw==":"mbr-12.jpeg","Gjo+fRcaTLdlEzWBcy0xQw==":"mbr-5.jpg","lNz+1WZ+Jsut4WEwqonaVg==":"mbr-7.jpg","r4SJW6vvdWfNTKjQSApHUw==":"mbr-8.jpg","aj6nI9PXScsDr4XezM2cNg==":"mbr-9.jpg","l3O6KHUARGL95+Th0X0BuQ==":"mbr-10.jpg","lK77ih7fT22RGPy5YZlknA==":"mbr-10.jpeg","9MA44v7wAXZf/YRNZxJK9Q==":"mbr-13.jpeg","uUTtwDNVtKLOj7cIFnet6w==":"mbr-14.jpeg","Q6iFla8InJcXTnXwrhQJBw==":"mbr-15.jpeg","r2I82yeII6avCvXJVP6Hhg==":"mbr-16.jpeg","/HVusEn4Av1iT9/R8YDOAA==":"mbr-11.jpg","CRxHHjX0jfgqDfEHqFpEbQ==":"mbr-17.jpeg","nZ522L3IHqZbQdLdB4urcw==":"mbr-18.jpeg","FUFWlmEDrx/Wq7juCg4sdQ==":"mbr-19.jpeg","kgPc6Z3mClKN6Ps+h/pg/Q==":"mbr-20.jpeg","AM3R9mKly8ZfHR+0fIrxNQ==":"img-3385-2000x2667.jpeg","MUvEuWli1jMCiFBsf777FQ==":"img-3386-2000x2667.jpeg","36NyglnAH88mZInDHt6+uQ==":"img-2183-2000x2667.jpeg","hbI0sKjCm5PXaJd/3CqRHw==":"img-2184-2000x2667.jpeg","v0v/JvIy9YxMft1PwwBGVw==":"img-2185-2000x2667.jpeg","em2EiK6NbxChc9DSoP6wZA==":"akss3160-2000x2667.jpeg","rsYkHAKUQFBoXCRtZ7Te1w==":"akss3160-1-2000x2667.jpeg","ON40HqBOv4x9/c0gwivlZQ==":"img-2183-1256x1675.jpeg","gJbsKPX21gNyhrKYwb8aTQ==":"img-1413-1022x1363.jpeg","CZuJvI6mq2mG/a1ATxyAVw==":"img-1157-1022x767.jpeg","fDz8YVeaydRUtNrQdxA0VQ==":"img-1181-1022x1363.jpeg","YrvSfus8f1lWaftDvO3IgA==":"img-2188-1022x1363.jpeg","dLTs30DsR56ByVwgLHye4g==":"img-1298-1022x1363.jpeg","wKqs1WIyxlS9ko6xuFo3dw==":"img-1393-1022x1363.jpeg","brKJ31sGQh1C38iupJqcpw==":"img-1733-816x612.jpg","D+4q6BZUwbv+DcSU5wBSnQ==":"img-2405-816x1088.jpeg","fuNI29TSFQpF+orZfRvjtw==":"img-1733-816x612.jpeg","kCFYwmITmYXfuWdKPhyK0Q==":"img_e3445-816x293.jpg","ViImDdJ/7N9EZiFdSbVH2Q==":"img_e3445-816x293.jpeg","zX7KwljsrmCUjtRjiedFLA==":"img-1397-2576x3435.jpeg","6OSTvBpYmgFAsWtZF+4DiA==":"img-2406-816x1088.jpeg","rtdu1jKm6qfQr+o9kjNXjg==":"img-1629-1256x1675.jpeg","YeenohCYBpJqklzGcvoQxQ==":"img-1059-816x1088.jpg","XRtAGe1qZ0+R6dLK5JPOBQ==":"img-1059-816x1088.jpeg","yOwT+hYqDedgpbhWcPoNSw==":"xcsb1811-816x612.jpg","VYBcgl7rkYrGpnfrbC5TFg==":"mpxd8617-816x1088.jpg","IhOESUw3095sZj8OuoDSfQ==":"img-2408-816x1088.jpeg","oe46gv/pMjn/UF54FQRsYg==":"img_e1249-1256x1675.jpg","g410c0FdxhW+3Crz1q3Ldg==":"img-1489-1256x1675.jpeg","mG6UvGm8bIJz19XADy6XJA==":"img-1480-1256x1675.jpeg","VGNKKfpv/JjfCXL8E8mz1Q==":"akss3160-2-2000x2667.jpeg","edmz5tGPaElu6xsVenDVxA==":"akss3160-3-2000x2667.jpeg","9hPu6LMEnSVytcbsdjIi4Q==":"akss3160-4-2000x2667.jpeg","ZpZdu223Fa5iYB2g+iiH3g==":"img-1059-2000x2667.jpeg","Qs6QxaXsTUPhRVT8cgPkhA==":"img-1589-2000x2667.jpeg","SQr+I6YzZzPRV+91uy8n3w==":"img-2157-120x160.jpeg","0hoX7oB0O+qY7Y8onBCiNA==":"img-1649-2000x2667.jpeg","z/vLAdH1WlTUDR3jJ2/WLA==":"img-1481-1256x1675.jpeg","wvFLlhvlZEkxcQVpb5Gopg==":"img-2184-1256x1675.jpeg","rBt/lfXLq8vPFiCshXqz+Q==":"img-2185-1256x1675.jpeg","iQhF4o6zWe2E2YqmJmWRQA==":"img-2183-1823x2431.jpeg","XR4voUAH82olEfPz+NgKyQ==":"img-3823-591x1280.png","0GEYOMUeH5TzsqqMmHffFw==":"img-3824-591x1280.png","jUuXFMIZ0WKuQSj4gTM8Hg==":"img-3822-591x1280.png","nYkKbHzrPppEXqdMVjnVYQ==":"img-1650-2000x2667.jpeg","9NOVkEbT3H7JV9IzuHCLcw==":"img-2206-1256x942.jpg","bKzQbmMPvUSXixHhkL3G0g==":"img-2352-1256x1675.jpeg","1Izcuqv9I5xG3zahOusdqA==":"img-2353-1256x1675.jpeg","9be3f9ya0/m+nttT1Cu25A==":"img-2354-1256x1675.jpeg","9WOBieSx944xKNHQGNrcuw==":"img-1060-816x1088.jpeg","LWBvA031Mx8OVm8Zxmdjrw==":"img-1202-942x1256.jpeg","fHWzV1dW5ew+KTstiGjviA==":"img-1185-942x1256.jpeg","OdNk5geeCRjQRCiNrQz0bw==":"img-7328-1256x1675.jpeg","zxbqSgtMUmPTK6Vt6E00Mw==":"img-7329-1256x1675.jpeg","jqz4p3Kk/OZRGU5/fHUN+w==":"img-7327-3024x4032.jpg","2RiWSBrBjs8EFVLDD7wnJA==":"img-7999-942x1256.jpeg","u6NkQjEX4iHXQIDciaQWWg==":"img_e8017-942x1256.jpeg","W1JVSfwMbxT39KdR1r3UEg==":"img-7969-942x1256.jpeg","wIeosAl/vOzBdwdKJwFF2A==":"img-7985-942x1256.jpeg","Hn5GgOzd7xVGaIftYj0VYA==":"img-484-750x1334.jpeg","kwZgaVxUkKPYsfaLNiVmPw==":"img-485-750x1334.jpeg","u/L+8+6xlgtMu8/cPkbU2A==":"img-486-750x1334.jpeg","CT+IqUzNHGY9T/pvMvjmTw==":"img-487-750x1334.jpeg","SZJIGyYMm6A3OhQwHze9kw==":"img-484-750x1334.jpg","gmIVqSjXhBkZQX8yTniXfg==":"img-2409-816x1088.jpeg","eSiuKPjUaH6H8MMzBIF9uA==":"img-1734-816x612.jpeg","aQxcHtf8Fb0noY+mfeZGsQ==":"img-2410-816x1088.jpeg","nmF4uqnxobD4b4Wd86fP9Q==":"img-488-750x1334.jpeg","+rNM1CNm0aWnjN9YDd3J2w==":"img-1735-816x612.jpeg","Rr91uKRPMU3Cknc2v3sGfg==":"img-2411-816x1088.jpeg","M0EDQpd7jUVvPvNB52Q5og==":"img-489-750x1334.jpeg","+JU417UoYWCM4heXAWzVzg==":"img-2923-942x1256.jpeg","J6TqZAVQ/rqSWp3FtVaH5A==":"img-1651-2000x2667.jpeg","BKhg74skqpRmWOPWDWsH+A==":"img-2910-2000x2667.jpg","ITV6Fe8L35o9qJjfPv3irA==":"img-2910-2000x2667.jpeg","mTrh60hIlF4oqvRdM64ZWQ==":"img-1138-2000x2667.jpg","ua5njiYFjEPkdFMP8xtLiw==":"img-8333-2000x2667.jpg","miUVsV7Ge+QBjIcjrIPy7w==":"img-5520-2000x2667.jpeg","olc7RmDoW/qNHhr+kDWucg==":"img-5520-2000x2763.jpeg","vDhER/iAel6lKcENHdeE9Q==":"img-5521-2000x2763.jpeg","EzNpsQ5ns9UmtbPoo9FKWw==":"img-5522-2000x2763.jpeg","oQGTJ96l8XZ5pzfUX6t/+w==":"img-5523-2000x2763.jpeg","gGve0JyLab4OrZWobfdpmw==":"img-5524-2000x2763.jpeg","zUjSgeHRlM6QqMVF/TNOfA==":"img-5522-2000x2706.jpg","1OdGtSRYtYrl05jWlbEBTw==":"img_5522b-2000x2706.jpg","oRykAiO0rUD++7AmPeEwUg==":"background1.jpg","yLDLt4x/yhmVO9yhu8cSYQ==":"team4.jpg","Vb7GgbMoe0curpGYBParsg==":"background3.jpg","Cesjxe6cW0NYFSAP4kiRig==":"features1.jpg","703jGkvtoXpxbZTG7S89UA==":"features2.jpg","HUfpc9SvDwBk7sbVG2SgiA==":"features3.jpg","WeIcOp+qLfFEPxVAXUUAEA==":"features4.jpg","VieXBz9DmcYwYpJVz/ugDw==":"img_5522b-2000x2706.jpeg","vStSc2AUU1H+eIPR9yRxXg==":"img_5522b-1-2000x2706.jpeg","4/vfarHz0F+4rQeJWF5fow==":"img-5105-816x1088.jpeg","6snBm5Vz9oGxsPp3ouPyqA==":"img_e4897-816x1088.jpg","Z2zLr/1kmRyuiGSXGqNrhw==":"img_e4897-816x1088.jpeg","tVlZzLtHPIDSS7inwQyyXw==":"img-5775-1288x1717.jpeg","WW25/OTcjKa38i78EODXgA==":"img-5927-1288x1717.jpeg","zaWyyYIGi+6WN+phxwFYNw==":"img-6163-1288x1717.jpeg","WM+p87O9tYIj8OwhsxgP9A==":"img-6217-1288x1717.jpeg","HtjFCSAClquQd1eG81HVKg==":"img-1202-596x795.jpeg","chRWlyDJBO/mosjJ4agp5Q==":"img-6258-596x795.jpeg","INYqK8zEAeCb8baobIPHLw==":"img-6372-596x795.jpeg","8MhP65M1RlEuMei/PQ6NsQ==":"img-6344-596x795.jpeg","uLPTL25YNW6q2FNaWabx8Q==":"img-6381-596x795.jpeg","glrBiBe6w+KiJ3VOfl8ong==":"img-6358-596x795.jpeg","MAwGd9gV6iOC+2DHNt+bog==":"img-6360-596x795.jpeg","qzZvv/L7IZON0jdYJkND2Q==":"img-6593-596x795.jpeg","UYSe/4uqRlho9QSLs7wNjw==":"rejsy2023-956x907.jpg","BTsCJPHAEARDiztU1m1UmA==":"img-2412-816x1088.jpeg","3imyxgAMWgO9ztpM/Vu8YA==":"img-1736-816x612.jpeg","TfUS83c/3ij4CHDKfDRiXQ==":"plan%20rejsu%202023%20kopia-956x907.jpg","ZIvvZZb5/60CoJluonES9w==":"img-7777-816x1088.jpeg","UvdW+UFIBsyZFBbCOjKVQQ==":"plan%20rejsu%202023%20b-956x907.jpg","/hrofmatROmm5vdXzEU7fw==":"rejs-sezon2024%20kopia-1031x792.jpg","vICprpQnhTxFnhzKVXBxSQ==":"rejs-sezon2024%20kopia-1031x792.jpeg","IKmC3m/RSBa9/8DQuVNKAA==":"rejs-sezon2024%20kopia-1031x792.jpeg","QKrxDExICkcfdZDx5s9zkA==":"sezon2024%20kopia2-1696x1350.jpg","X3s1n5ovmmrIi3qB3AHiEQ==":"sezon2025%20kopia-1696x1350.jpg"}